MANIFEST.in
README.rst
setup.py
tawnycalc/LICENSE
tawnycalc/__init__.py
tawnycalc/_version.py
tawnycalc/chemical_system.py
tawnycalc/core.py
tawnycalc/data_objects.py
tawnycalc.egg-info/PKG-INFO
tawnycalc.egg-info/SOURCES.txt
tawnycalc.egg-info/dependency_links.txt
tawnycalc.egg-info/requires.txt
tawnycalc.egg-info/top_level.txt
tawnycalc/bin/thermo_Darwin
tawnycalc/bin/thermo_Linux
tawnycalc/bin/thermo_Windows
tawnycalc/datasets/oxide_data.txt
tawnycalc/datasets/tc-ds62.txt
tawnycalc/datasets/tc-ds633.txt
tawnycalc/datasets/tc-ig50NCKFMASHTOCr.txt
tawnycalc/datasets/tc-ig50NCKFMASTOCr.txt
tawnycalc/datasets/tc-mb50NCKFMASHTO.txt
tawnycalc/datasets/tc-mp50KFMASH.txt
tawnycalc/datasets/tc-mp50MnNCKFMASHTO.txt
tawnycalc/datasets/tc-mp50NCKFMASHTO.txt