Metadata-Version: 1.1
Name: tawnycalc
Version: 0.4.1
Summary: Python wrappers for THERMOCALC software for phase equilibrium modelling.
Home-page: https://github.com/underworldcode/tawnycalc
Author: John Mansour
Author-email: mansourjohn@gmail.com
License: LGPL-3
Platform: UNKNOWN
Provides: tawnycalc
